khmerencoding/__init__.py
khmerencoding/encoding.py
khmerencoding-0.1.1.dist-info/LICENSE
khmerencoding-0.1.1.dist-info/METADATA
khmerencoding-0.1.1.dist-info/WHEEL
khmerencoding-0.1.1.dist-info/top_level.txt
khmerencoding-0.1.1.dist-info/RECORD
