Metadata-Version: 2.1
Name: khmerencoding
Version: 0.1.1
Summary: Khmer character encoding based on the [khmer character specification](https://github.com/sillsdev/khmer-character-specification).
Home-page: https://github.com/maohieng/khmerencoding
Author: Hieng MAO
Author-email: maohieng@gmail.com
License: Apache License 2.0
Classifier: Programming Language :: Python :: 3
Classifier: Operating System :: OS Independent
Classifier: Intended Audience :: Developers
Classifier: Natural Language :: English
Requires-Python: >=3.5
License-File: LICENSE
